lazyclass/__init__.py
lazyclass-1.0.0.dist-info/METADATA
lazyclass-1.0.0.dist-info/WHEEL
lazyclass-1.0.0.dist-info/top_level.txt
lazyclass-1.0.0.dist-info/RECORD
