Metadata-Version: 2.1
Name: lazyclass
Version: 1.0.0
Summary: Class for lazy adding of methods and properties
Home-page: https://gitlab.com/resolvedinstruments/lazyclass
Author: Callum Doolin
Author-email: callum@resolvedinstruments.com
License: MIT
Platform: UNKNOWN
Classifier: License :: OSI Approved :: MIT License
Classifier: Programming Language :: Python :: 3.6
Classifier: Programming Language :: Python :: 3.7
Classifier: Programming Language :: Python :: 3.8
Classifier: Programming Language :: Python :: 3.9
Requires-Python: >=3.6
